{
  "metadata": {
    "servers": [],
    "blacklist": false,
    "universal": true
  },
  "items": [
    {
      "languages": {
        "en_US": "&fWelcome to &a6lSurvivalIsland!",
        "ja_JP": "&a&lSurvivalIsland &fへようこそ！"
      },
      "type": "text",
      "_twin": {
        "dateCreated": 1593445602280,
        "id": "835d7c35-1619-4c3a-a5ba-59fb7c493105",
        "dateUpdated": 1593446582494
      },
      "key": "survivalisland.hologram.welcome.1"
    },
    {
      "languages": {
        "en_US": "To get started:",
        "ja_JP": "開始するには："
      },
      "type": "text",
      "_twin": {
        "dateCreated": 1593445697496,
        "id": "7f1acccb-d20a-4efd-9e80-2a442c09df78",
        "dateUpdated": 1593445793524
      },
      "key": "survivalisland.hologram.welcome.2"
    }
  ]
}